LICENSE.txt
MANIFEST.in
README.md
setup.py
kgbase/Query.py
kgbase/__init__.py
kgbase.egg-info/PKG-INFO
kgbase.egg-info/SOURCES.txt
kgbase.egg-info/dependency_links.txt
kgbase.egg-info/requires.txt
kgbase.egg-info/top_level.txt
kgbase/graphql/mutation/BulkDeleteVertices.graphql
kgbase/graphql/mutation/BulkStartImport.graphql
kgbase/graphql/mutation/BulkStartProcessing.graphql
kgbase/graphql/mutation/CreateColumn.graphql
kgbase/graphql/mutation/CreateProject.graphql
kgbase/graphql/mutation/CreateTable.graphql
kgbase/graphql/mutation/CreateVertex.graphql
kgbase/graphql/mutation/DeleteColumn.graphql
kgbase/graphql/mutation/DeleteTable.graphql
kgbase/graphql/mutation/DeleteVertex.graphql
kgbase/graphql/mutation/DestroyProject.graphql
kgbase/graphql/mutation/LoginUser.graphql
kgbase/graphql/mutation/LogoutUser.graphql
kgbase/graphql/mutation/UpdateColumn.graphql
kgbase/graphql/mutation/UpdateProject.graphql
kgbase/graphql/mutation/UpdateTable.graphql
kgbase/graphql/mutation/UpdateVertex.graphql
kgbase/graphql/mutation/UploadFile.graphql
kgbase/graphql/query/GetBulkBundle.graphql
kgbase/graphql/query/GetBulkUploads.graphql
kgbase/graphql/query/GetFavoriteProjects.graphql
kgbase/graphql/query/GetGraph.graphql
kgbase/graphql/query/GetProjectState.graphql
kgbase/graphql/query/GetPublicProjects.graphql
kgbase/graphql/query/GetSchema.graphql
kgbase/graphql/query/GetTask.graphql
kgbase/graphql/query/GetTeamProjects.graphql
kgbase/graphql/query/GetUserProjects.graphql
kgbase/graphql/query/GetUserState.graphql
kgbase/graphql/query/PreviewBulkBundle.graphql
kgbase/graphql/query/SummarizeGraph.graphql