Metadata-Version: 2.1
Name: kgbase
Version: 0.36
Summary: UNKNOWN
Home-page: https://kgbase.com
Author: Kgbase
Author-email: customersuccess@thinknum.com
License: MIT
Download-URL: https://github.com/thinknum/kgbase-client
Keywords: Kgbase,Thinknum,Alternative data,Data
Platform: UNKNOWN
Classifier: Development Status :: 5 - Production/Stable
Classifier: Intended Audience :: Developers
Classifier: Topic :: Software Development :: Build Tools
Classifier: License :: OSI Approved :: MIT License
Classifier: Programming Language :: Python :: 2
Classifier: Programming Language :: Python :: 3
Classifier: Programming Language :: Python :: 3.4
Classifier: Programming Language :: Python :: 3.5
Classifier: Programming Language :: Python :: 3.6
License-File: LICENSE.txt
